pcolory/__init__.py
pcolory/colors.py
pcolory/pcolory.py
pcolory-0.1.2.dist-info/licenses/LICENSE
pcolory-0.1.2.dist-info/METADATA
pcolory-0.1.2.dist-info/WHEEL
pcolory-0.1.2.dist-info/top_level.txt
pcolory-0.1.2.dist-info/RECORD
