Metadata-Version: 2.4
Name: pcolory
Version: 0.1.2
Summary: A library that can make print() colorful.
Author-email: Yongzi Li <1538321957@qq.com>
License:                                  Apache License
Project-URL: Homepage, https://github.com/Yzi-Li/pcolory
Classifier: Development Status :: 4 - Beta
Classifier: Programming Language :: Python :: 3.10
Classifier: Programming Language :: Python :: 3.11
Classifier: Programming Language :: Python :: 3.12
Classifier: Programming Language :: Python :: 3.13
Classifier: Intended Audience :: Developers
Classifier: License :: OSI Approved :: Apache Software License
Classifier: Operating System :: OS Independent
Requires-Python: >=3.10
License-File: LICENSE
Dynamic: license-file
